fustor_source_fs/__init__.py
fustor_source_fs/components.py
fustor_source_fs/event_handler.py
fustor_source_fs/py.typed
fustor_source_fs-0.2.16.dist-info/METADATA
fustor_source_fs-0.2.16.dist-info/WHEEL
fustor_source_fs-0.2.16.dist-info/entry_points.txt
fustor_source_fs-0.2.16.dist-info/top_level.txt
fustor_source_fs-0.2.16.dist-info/RECORD
