Metadata-Version: 2.4
Name: fustor-source-fs
Version: 0.2.16
Summary: Fustor Agent FS Source Driver
License-Expression: MIT
Requires-Dist: fustor-core
Requires-Dist: fustor-event-model
Requires-Dist: watchdog
